aixpress/__init__.py
aixpress-0.0.0.1.dist-info/LICENSE
aixpress-0.0.0.1.dist-info/METADATA
aixpress-0.0.0.1.dist-info/WHEEL
aixpress-0.0.0.1.dist-info/top_level.txt
aixpress-0.0.0.1.dist-info/RECORD
